strings2df/Eula.txt
strings2df/README.md
strings2df/__init__.py
strings2df/requirements.txt
strings2df/strings.exe
strings2df/strings64.exe
strings2df/strings64a.exe
strings2df/thirdparty.json
strings2df-0.10.dist-info/LICENSE.rst
strings2df-0.10.dist-info/METADATA
strings2df-0.10.dist-info/WHEEL
strings2df-0.10.dist-info/top_level.txt
strings2df-0.10.dist-info/RECORD
