Metadata-Version: 2.1
Name: strings2df
Version: 0.10
Summary: Results of strings.exe to pandas DataFrame
Home-page: https://github.com/hansalemaos/strings2df
Author: Johannes Fischer
Author-email: aulasparticularesdealemaosp@gmail.com
License: MIT
Keywords: strings,extract
Classifier: Development Status :: 4 - Beta
Classifier: Programming Language :: Python :: 3 :: Only
Classifier: Programming Language :: Python :: 3.10
Classifier: Topic :: Software Development :: Libraries :: Python Modules
Classifier: Topic :: Utilities
License-File: LICENSE.rst
Requires-Dist: a-pandas-ex-df-to-string
Requires-Dist: a-pandas-ex-fastloc
Requires-Dist: a-pandas-ex-horizontal-explode
Requires-Dist: getfilenuitkapython
Requires-Dist: list-all-files-recursively
Requires-Dist: multisubprocess
Requires-Dist: numpy
Requires-Dist: pandas
Requires-Dist: regex
